pycryptomator/4096words_en.txt
pycryptomator/__init__.py
pycryptomator/__main__.py
pycryptomator/cmshell.py
pycryptomator/cryptomator.py
pycryptomator/wordscodec.py
pycryptomator/w32lex/__init__.py
pycryptomator-1.14.dist-info/LICENSE
pycryptomator-1.14.dist-info/METADATA
pycryptomator-1.14.dist-info/WHEEL
pycryptomator-1.14.dist-info/entry_points.txt
pycryptomator-1.14.dist-info/top_level.txt
pycryptomator-1.14.dist-info/RECORD
