Metadata-Version: 2.1
Name: pycryptomator
Version: 1.14
Summary: Access a Cryptomator V8 vault with pure Python
Author-email: maxpat78 <maxpat78@yahoo.it>
License: MIT License
Project-URL: Homepage, https://github.com/maxpat78/pycryptomator
Project-URL: Source, https://github.com/maxpat78/pycryptomator
Keywords: cryptomator,python,crypto,encryption,security,privacy,cryptography,vault
Classifier: Development Status :: 5 - Production/Stable
Classifier: Intended Audience :: System Administrators
Classifier: License :: OSI Approved :: MIT License
Classifier: Programming Language :: Python :: 3 :: Only
Requires-Python: >=3.0
License-File: LICENSE
Requires-Dist: pycryptodome>=3.21
